cyksuid/hints.py
cyksuid/_ksuid.pxd
cyksuid/_ksuid.pyi
cyksuid/_ksuid.cpython-39-x86_64-linux-gnu.so
cyksuid/__version__.py
cyksuid/fast_base62.pyx
cyksuid/_ksuid.pyx
cyksuid/ksuid.py
cyksuid/cbase62.cc
cyksuid/fast_base62.pxd
cyksuid/fast_base62.cpp
cyksuid/ksuidlite.h
cyksuid/fast_base62.cpython-39-x86_64-linux-gnu.so
cyksuid/cbase62.h
cyksuid/_ksuid.cpp
cyksuid/__init__.py
cyksuid/py.typed
cyksuid/fast_base62.pyi
cyksuid/v2.py
cyksuid-2.1.0.dist-info/LICENSE
cyksuid-2.1.0.dist-info/METADATA
cyksuid-2.1.0.dist-info/RECORD
cyksuid-2.1.0.dist-info/WHEEL
cyksuid-2.1.0.dist-info/top_level.txt
cyksuid.libs/libstdc++-a9383cce.so.6.0.28
cyksuid.libs/libgcc_s-a04fdf82.so.1
